pynufft/__init__.py
pynufft/linalg/__init__.py
pynufft/linalg/nudft_cpu.py
pynufft/linalg/nudft_cupy.py
pynufft/linalg/nufft_cpu.py
pynufft/linalg/nufft_cupy.py
pynufft/linalg/nufft_hsa.py
pynufft/linalg/nufft_hsa_legacy.py
pynufft/linalg/solve_cpu.py
pynufft/linalg/solve_device.py
pynufft/linalg/solve_hsa.py
pynufft/linalg/solve_legacy.py
pynufft/nufft/__init__.py
pynufft/nufft/_nufft_class_methods_cpu.py
pynufft/nufft/_nufft_class_methods_device.py
pynufft/src/__init__.py
pynufft/src/__init__.pyc
pynufft/src/re_subroutine.py
pynufft/src/texput.log
pynufft/src/_helper/Nd_tensor.py
pynufft/src/_helper/__init__.py
pynufft/src/_helper/__init__.pyc
pynufft/src/_helper/helper.py
pynufft/src/_helper/helper.pyc
pynufft/src/data/__init__.py
pynufft/src/data/om1D.npz
pynufft/src/data/om2D.npz
pynufft/src/data/om3D.npz
pynufft/src/data/phantom_256_256.npz
pynufft/src/data/phantom_3D_128_128_128.npz
pynufft/tests/__init__.py
pynufft/tests/parallel_NUFFT.py
pynufft/tests/script_2D.py
pynufft/tests/test_cupy.py
pynufft/tests/test_init.py
pynufft/tests/test_init_device.py
pynufft/tests/test_radial.py
pynufft/tests/test_tf_eager.py
pynufft/tests/test_torch.py
pynufft/tests/tmp2d_1_.mat
pynufft/tests/tmp2d_2_.mat
pynufft/tests/tmp2d_3_.mat
pynufft-2025.1.1.dist-info/LICENSE
pynufft-2025.1.1.dist-info/METADATA
pynufft-2025.1.1.dist-info/WHEEL
pynufft-2025.1.1.dist-info/top_level.txt
pynufft-2025.1.1.dist-info/RECORD
