Metadata-Version: 2.1
Name: pynufft
Version: 2025.1.1
Summary: Python non-uniform fast Fourier transform (PyNUFFT)
Home-page: https://github.com/jyhmiinlin/pynufft
Author: PyNUFFT
Author-email: pynufft@gmail.com
License: The MIT License
License-File: LICENSE
Requires-Dist: numpy
Requires-Dist: scipy
